<?xml version="1.0" encoding="utf-8"?>
<optionset Name="rpo_feedingquantity" localizedName="Feeding Quantity" xmlns:xsi="http://www.w3.org/2001/XMLSchema-instance">
  <OptionSetType>picklist</OptionSetType>
  <IsGlobal>1</IsGlobal>
  <IntroducedVersion>1.0.0</IntroducedVersion>
  <IsCustomizable>1</IsCustomizable>
  <ExternalTypeName></ExternalTypeName>
  <displaynames>
    <displayname description="Feeding Quantity" languagecode="1033" />
  </displaynames>
  <Descriptions>
    <Description description="" languagecode="1033" />
  </Descriptions>
  <options>
    <option value="913610000" ExternalValue="">
      <labels>
        <label description="10" languagecode="1033" />
      </labels>
      <Descriptions>
        <Description description="" languagecode="1033" />
      </Descriptions>
    </option>
    <option value="913610001" ExternalValue="">
      <labels>
        <label description="50" languagecode="1033" />
      </labels>
      <Descriptions>
        <Description description="" languagecode="1033" />
      </Descriptions>
    </option>
    <option value="913610002" ExternalValue="">
      <labels>
        <label description="100" languagecode="1033" />
      </labels>
      <Descriptions>
        <Description description="" languagecode="1033" />
      </Descriptions>
    </option>
    <option value="913610003">
      <labels>
        <label description="1000" languagecode="1033" />
      </labels>
      <Descriptions>
        <Description description="" languagecode="1033" />
      </Descriptions>
    </option>
  </options>
</optionset>